solveit_dmtools/__init__.py
solveit_dmtools/_modidx.py
solveit_dmtools/dhb.py
solveit_dmtools/dhp.py
solveit_dmtools/fab.py
solveit_dmtools-0.0.18.dist-info/licenses/LICENSE
solveit_dmtools-0.0.18.dist-info/METADATA
solveit_dmtools-0.0.18.dist-info/WHEEL
solveit_dmtools-0.0.18.dist-info/entry_points.txt
solveit_dmtools-0.0.18.dist-info/top_level.txt
solveit_dmtools-0.0.18.dist-info/RECORD
